Workbook

Sheet Risk Analysis
A1: Functional Area | B1: Reason | C1: Impact on FCF | D1: Systemic Risks | E1: Non-Systemic Risks
A2: IT & Systems | B2: Cybersecurity, IT Systems
A3: Procurement | B3: Vendor Management, Contracts, Sourcing
A4: Finance | B4: Budgeting, Debt/Equity Ratio, pay later | C4: FCF= EBIT (1-T) + Depreciation - CAPEX - Increase in Net Working Capital 1) Paying third party later will increase net working capital (NWC = Cash + Inventory + Recievable = Payable) 2) Advertise certificates to commericial clients to increase revenue (/EBIT) 3) Utilize CAPEX to reduce T | D4: Increase debt for capital expenditure will change WACC (WACC = E/(E+D)*re + D/(E+D)"rd*(1-T) This will change NPV | E4: Competitors also get certificates and we can not enjoy the growth. Government decided to obligate the certification not allowing additional price for the contracts.
A5: HR | B5: Training related issues (ie. not enough cyber security human resource in the market, salary increase) | C5: FCF= EBIT (1-T) + Depreciation - CAPEX - Increase in Net Working Capital 1) Cost overrun of training and/or hiring 2) Salary increse over the years | D5: talent scarcity | E5: Lack of resouorce leads to failure of getting a certificate or security incidents. | F5: https://www.mxdusa.org/news/6-cmmc-tips-choosing-a-third-party-assessor-c3pao/#:~:text=There%20are%20an%20estimated%20118%2C000,C3PAO%20may%20not%20be%20easy.

Sheet Assumptions
B1: Value | C1: Formula | D1: Notes
A2: Expected Base Revenue | B2: =[1]KPIs!$B$9 -> 3555000 | C2: =IFERROR(_xlfn.FORMULATEXT(B2),B2) -> ='C:\Users\emily\Documents\Product Management Portfolio\[Customer Data with Clusters.xlsx]KPIs'!$B$9
A3: Yearly Revenues from Investment | B3: =[1]KPIs!$B$10 -> 695000 | C3: =IFERROR(_xlfn.FORMULATEXT(B3),B3) -> ='C:\Users\emily\Documents\Product Management Portfolio\[Customer Data with Clusters.xlsx]KPIs'!$B$10
A4: Avg Industry CAGR | B4: =ROUND('Average Industry Growth'!D17,2) -> 0.07 | C4: =IFERROR(_xlfn.FORMULATEXT(B4),B4) -> =ROUND('Average Industry Growth'!D17,2) | D4: Based on average industry revenue growth over the past 4 years
A5: Perpetual Growth Rate | B5: 0.015 | C5: =IFERROR(_xlfn.FORMULATEXT(B5),B5) -> 0.015 | D5: Reasonable estimate, less than GDP growth
A6: Average Industry Gross Margin | B6: =ROUND('Average Industry Growth'!B30,2) -> 0.36 | C6: =IFERROR(_xlfn.FORMULATEXT(B6),B6) -> =ROUND('Average Industry Growth'!B30,2) | D6: Would use actual*
A7: Gross Margin of Project | B7: =B6 -> 0.36 | C7: =IFERROR(_xlfn.FORMULATEXT(B7),B7) -> =B6 | D7: Essentially the same, given increases in revenue and expenses
A8: Investment | B8: ='Cost Data'!G22 -> 351000 | C8: =IFERROR(_xlfn.FORMULATEXT(B8),B8) -> ='Cost Data'!G22
A9: Avg Industry Tax Rate | B9: ='Average Industry Growth'!B38 -> 0.2284 | C9: =IFERROR(_xlfn.FORMULATEXT(B9),B9) -> ='Average Industry Growth'!B38 | D9: Would use actual*
A10: Depreciation | B10: 0 | C10: =IFERROR(_xlfn.FORMULATEXT(B10),B10) -> 0

Sheet Cost Data
A1: Initial Investment
A2: Category | B2: Cost Item | C2: Cost Type | D2: Low Estimate ($) | E2: High Estimate ($) | F2: Variable Amt. | G2: Average Cost | H2: Notes | I2: Source
A3: Core Product Development | B3: Engineering labor (frontend + backend developers) | C3: One-time | D3: 30000 | E3: 100000 | F3: 1 | G3: =((D3*F3)+(E3*F3))/2 -> 65000
A4: Core Product Development | B4: UI/UX design | C4: One-time | D4: 5000 | E4: 20000 | F4: 1 | G4: =((D4*F4)+(E4*F4))/2 -> 12500
A5: Core Product Development | B5: Product management / project management | C5: One-time | D5: 5000 | E5: 15000 | F5: 1 | G5: =((D5*F5)+(E5*F5))/2 -> 10000
A6: Core Product Development | B6: QA / testing | C6: One-time | D6: 5000 | E6: 15000 | F6: 1 | G6: =((D6*F6)+(E6*F6))/2 -> 10000
A7: Core Product Development | B7: Third-party integrations (chat APIs, SDKs setup) | C7: One-time | D7: 5000 | E7: 20000 | F7: 1 | G7: =((D7*F7)+(E7*F7))/2 -> 12500
A8: Core Product Development | B8: DevOps / deployment setup | C8: One-time | D8: 5000 | E8: 15000 | F8: 1 | G8: =((D8*F8)+(E8*F8))/2 -> 10000
A9: Backend Infrastructure | B9: Initial cloud setup + first-year hosting | C9: Yearly | D9: 10000 | E9: 50000 | F9: 1 | G9: =((D9*F9)+(E9*F9))/2 -> 30000
A10: Backend Infrastructure | B10: Messaging APIs (initial usage + setup) | C10: Yearly | D10: 5000 | E10: 30000 | F10: 1 | G10: =((D10*F10)+(E10*F10))/2 -> 17500
A11: Backend Infrastructure | B11: Data storage & pipeline setup | C11: Yearly | D11: 5000 | E11: 20000 | F11: 1 | G11: =((D11*F11)+(E11*F11))/2 -> 12500
A12: AI / Chatbot Layer | B12: NLP chatbot development | C12: One-time | D12: 10000 | E12: 30000 | F12: 1 | G12: =((D12*F12)+(E12*F12))/2 -> 20000
A13: AI / Chatbot Layer | B13: Initial AI model setup / first-year usage | C13: Yearly | D13: 5000 | E13: 20000 | F13: 1 | G13: =((D13*F13)+(E13*F13))/2 -> 12500
A14: Customer Support | B14: Initial outsourced support (first 3–6 months ramp) | C14: One-time | D14: 6000 | E14: 60000 | F14: 1 | G14: =((D14*F14)+(E14*F14))/2 -> 33000
... A21: Legal & Admin | B21: Contracts & legal support | C21: One-time | D21: 5000 | E21: 10000 | F21: 1 | G21: =((D21*F21)+(E21*F21))/2 -> 7500
G22: =SUM(G3:G21) -> 351000
A24: Yearly | B24: =SUMIF(C3:G21,A24,G3:G21) -> 95000

Sheet Average Industry Growth
A1: Revenues
B2: Year 4 | C2: Year 3 | D2: Year 2 | E2: Year 1 | F2: Source | G2: Growth Rate | H2: Formulas
A3: Amazon | B3: 716924000000 | C3: 637959000000 | D3: 574785000000 | E3: 513983000000 | F3: Amazon.com, Inc. (AMZN) Income Statement - Yahoo Finance | G3: =(B3-E3)/E3 -> 0.39483991 | H3: =_xlfn.FORMULATEXT(G3) -> =(B3-E3)/E3
A4: Walmart | B4: 713163000000 | C4: 680985000000 | D4: 648125000000 | E4: 611289000000 | F4: Walmart Inc. (WMT) Income Statement - Yahoo Finance | G4: =(B4-E4)/E4 -> 0.1666544 | H4: =_xlfn.FORMULATEXT(G4) -> =(B4-E4)/E4
A5: Alibaba | B5: 996347000000 | C5: 941168000000 | D5: 868687000000 | E5: 853062000000 | F5: Alibaba Group Holding Limited (BABA) Income Statement - Yahoo Finance | G5: =(B5-E5)/E5 -> 0.16796552 | H5: =_xlfn.FORMULATEXT(G5) -> =(B5-E5)/E5
A7: Average | G7: =AVERAGE(G3:G4) -> 0.28074715 | H7: =_xlfn.FORMULATEXT(G7) -> =AVERAGE(G3:G4)
A8: Average of our comps | G8: =AVERAGE(G3:G4) -> 0.28074715 | H8: =_xlfn.FORMULATEXT(G8) -> =AVERAGE(G3:G4)
A10: Average Year over Year Change | F10: Formulas
B11: Year 3-4 | C11: Year 2-3 | D11: Year 1 - 2 | G11: Year 3-4 | H11: Year 2-3 | I11: Year 1 - 2
A12: Amazon | B12: =(B3-C3)/C3 -> 0.12377755 | C12: =(C3-D3)/D3 -> 0.10990892 | D12: =(D3-E3)/E3 -> 0.11829574 | F12: Amazon | G12: =_xlfn.FORMULATEXT(B12) -> =(B3-C3)/C3 | H12: =_xlfn.FORMULATEXT(C12) -> =(C3-D3)/D3 | I12: =_xlfn.FORMULATEXT(D12) -> =(D3-E3)/E3
A13: Walmart | B13: =(B4-C4)/C4 -> 0.047252142 | C13: =(C4-D4)/D4 -> 0.050700096 | D13: =(D4-E4)/E4 -> 0.06025955 | F13: Walmart | G13: =_xlfn.FORMULATEXT(B13) -> =(B4-C4)/C4 | H13: =_xlfn.FORMULATEXT(C13) -> =(C4-D4)/D4 | I13: =_xlfn.FORMULATEXT(D13) -> =(D4-E4)/E4
A14: Alibaba | B14: =(B5-C5)/C5 -> 0.058628215 | C14: =(C5-D5)/D5 -> 0.083437418 | D14: =(D5-E5)/E5 -> 0.018316371 | F14: Alibaba | G14: =_xlfn.FORMULATEXT(B14) -> =(B5-C5)/C5 | H14: =_xlfn.FORMULATEXT(C14) -> =(C5-D5)/D5 | I14: =_xlfn.FORMULATEXT(D14) -> =(D5-E5)/E5
A16: Average | D16: =AVERAGE(B12:D14) -> 0.074508445 | F16: =_xlfn.FORMULATEXT(D16) -> =AVERAGE(B12:D14)
A17: Average of our comps | D17: =AVERAGE(D12:D14) -> 0.065623887 | F17: =_xlfn.FORMULATEXT(D17) -> =AVERAGE(D12:D14)
A20: Gross Profit
A21: Amazon | B21: 360510000000 | C21: 311671000000 | D21: 270046000000 | E21: 225152000000 | F21: Amazon.com, Inc. (AMZN) Income Statement - Yahoo Finance
A22: Walmart | B22: 177768000000 | C22: 169232000000 | D22: 157983000000 | E22: 147568000000 | F22: Walmart Inc. (WMT) Income Statement - Yahoo Finance
A23: Alibaba | B23: 398062000000 | C23: 354845000000 | D23: 318992000000 | E23: 313612000000 | F23: Alibaba Group Holding Limited (BABA) Income Statement - Yahoo Finance
A25: GM
A26: Amazon | B26: =B21/B3 -> 0.50285665 | C26: =C21/C3 -> 0.48854393 | D26: =D21/D3 -> 0.46982089 | E26: =E21/E3 -> 0.4380534
A27: Walmart | B27: =B22/B4 -> 0.249267 | C27: =C22/C4 -> 0.24851061 | D27: =D22/D4 -> 0.24375391 | E27: =E22/E4 -> 0.24140464
A28: Alibaba | B28: =B23/B5 -> 0.39952145 | C28: =C23/C5 -> 0.37702621 | D28: =D23/D5 -> 0.36721167 | E28: =E23/E5 -> 0.36763096
A30: Average | B30: =AVERAGE(B26:E27) -> 0.36027638
A33: Tax
A34: Amazon | B34: 0.196 | C34: Amazon's tax bill plunges after GOP tax cuts - POLITICO
A35: Walmart | B35: 0.234 | C35: Walmart 2025 Annual Report
A36: AliBaba | B36: 0.2552 | C36: https://www.financecharts.com/stocks/BABA/income-statement/tax-rate
A38: Average | B38: =AVERAGE(B34:B36) -> 0.2284
A41: Receivables
A42: Amazon | B42: 67729000000 | C42: Amazon.com, Inc. - 10K - Annual Report - February 6, 2026
A43: Walmart | B43: 9975000000 | C43: Walmart 2025 Annual Report
A44: Alibaba | B44: 129075000000 | C44: Alibaba Group Holding Limited (BABA) Balance Sheet - Yahoo Finance
A46: Receivables % of Sales
A47: Amazon | B47: =B42/B3 -> 0.094471659
A48: Walmart | B48: =B43/B4 -> 0.013986985
A49: Alibaba | B49: =B44/B5 -> 0.12954824
A51: Payables
A52: Amazon | B52: 94363000000
A53: Walmart | B53: 58666000000
A54: Alibaba | B54: 249158000000
A56: COGS
A57: Amazon | B57: 304739000000
A58: Walmart | B58: 511753000000
A59: Alibaba | B59: 598285000000
A61: Payables % of COGS
A62: Amazon | B62: =B52/B57 -> 0.30965187
A63: Walmart | B63: =B53/B58 -> 0.11463733
A64: Alibaba | B64: =B54/B59 -> 0.4164537

Sheet Bond Ratings
A1: Comps | B1: Credit Rating Agency | C1: Long Term Ratings | D1: Source | E1: Average Yield | F1: Source
A2: Amazon | B2: S&P | C2: AA | D2: from 10-k | E2: 0.0482 | F2: https://ycharts.com/indicators/us_corporate_aa_effective_yield
A3: Walmart | B3: Finch | C3: AA | D3: from 10-k | E3: 0.0482 | F3: https://ycharts.com/indicators/us_corporate_aa_effective_yield
A4: Alibaba | B4: S&P | C4: A | D4: from 10-k | E4: 0.0482 | F4: https://ycharts.com/indicators/us_corporate_aa_effective_yield

Sheet Ba Calculation
B1: Comps | C1: Be | D1: Net Debt | E1: Market Cap | F1: D/E | G1: D/V | H1: E/V | I1: S&P Bond Rating | J1: YTM | K1: Bd | L1: Ba (or Bu)
B2: Amazon | C2: 1.38 | D2: 0 | E2: 2690000000000 | F2: =D2/E2 -> 0 | G2: =F2/(F2+1) -> 0 | H2: =1-G2 -> 1 | I2: BBB | J2: ~5% | K2: 0.05 | L2: =G2*K2+H2*C2 -> 1.38 | N2: Amazon.com, Inc. (AMZN) Stock Price, News, Quote & History - Yahoo Finance
B3: Walmart | C3: 0.66 | D3: 30030000 | E3: 994640000000 | F3: =D3/E3 -> 3.0191828e-05 | G3: =F3/(F3+1) -> 3.0190917e-05 | H3: =1-G3 -> 0.99996981 | I3: BBB | J3: ~5% | K3: 0.05 | L3: =G3*K3+H3*C3 -> 0.65998158 | N3: Walmart Inc. (WMT) Income Statement - Yahoo Finance
B4: Alibaba | C4: 0.49 | D4: 0 | E4: 314090000000 | N4: Alibaba Group Holding Limited (BABA) Stock Price, News, Quote & History - Yahoo Finance
B5: Average | L5: =AVERAGE(L2:L4) -> 1.0199908
B7: Comps | C7: Be | D7: Net Debt | E7: Market Cap | F7: D/E | G7: D/V | H7: E/V | I7: S&P Bond Rating | J7: YTM | K7: Bd | L7: Ba (or Bu)
B8: Amazon | C8: =IFERROR(_xlfn.FORMULATEXT(C2),C2) -> 1.38 | D8: =IFERROR(_xlfn.FORMULATEXT(D2),D2) -> 0 | E8: =IFERROR(_xlfn.FORMULATEXT(E2),E2) -> 2690000000000 | F8: =IFERROR(_xlfn.FORMULATEXT(F2),F2) -> =D2/E2 | G8: =IFERROR(_xlfn.FORMULATEXT(G2),G2) -> =F2/(F2+1) | H8: =IFERROR(_xlfn.FORMULATEXT(H2),H2) -> =1-G2 | I8: =IFERROR(_xlfn.FORMULATEXT(I2),I2) -> BBB | J8: =IFERROR(_xlfn.FORMULATEXT(J2),J2) -> ~5% | ... L8: =IFERROR(_xlfn.FORMULATEXT(L2),L2) -> =G2*K2+H2*C2
B9: Walmart | C9: =IFERROR(_xlfn.FORMULATEXT(C3),C3) -> 0.66 | D9: =IFERROR(_xlfn.FORMULATEXT(D3),D3) -> 30030000 | E9: =IFERROR(_xlfn.FORMULATEXT(E3),E3) -> 994640000000 | F9: =IFERROR(_xlfn.FORMULATEXT(F3),F3) -> =D3/E3 | G9: =IFERROR(_xlfn.FORMULATEXT(G3),G3) -> =F3/(F3+1) | H9: =IFERROR(_xlfn.FORMULATEXT(H3),H3) -> =1-G3 | I9: =IFERROR(_xlfn.FORMULATEXT(I3),I3) -> BBB | J9: =IFERROR(_xlfn.FORMULATEXT(J3),J3) -> ~5% | ... L9: =IFERROR(_xlfn.FORMULATEXT(L3),L3) -> =G3*K3+H3*C3
B10: Alibaba | C10: =IFERROR(_xlfn.FORMULATEXT(C4),C4) -> 0.49 | D10: =IFERROR(_xlfn.FORMULATEXT(D4),D4) -> 0 | E10: =IFERROR(_xlfn.FORMULATEXT(E4),E4) -> 314090000000 | F10: =IFERROR(_xlfn.FORMULATEXT(F4),F4) -> 0 | G10: =IFERROR(_xlfn.FORMULATEXT(G4),G4) -> 0 | H10: =IFERROR(_xlfn.FORMULATEXT(H4),H4) -> 0 | I10: =IFERROR(_xlfn.FORMULATEXT(I4),I4) -> 0 | J10: =IFERROR(_xlfn.FORMULATEXT(J4),J4) -> 0 | ... L10: =IFERROR(_xlfn.FORMULATEXT(L4),L4) -> 0
B11: Average | L11: =IFERROR(_xlfn.FORMULATEXT(L5),L5) -> =AVERAGE(L2:L4)
B14: Company | C14: Be | D14: Net Debt | E14: Market Cap | F14: D/E | G14: D/V | H14: E/V | I14: S&P Bond Rating | J14: YTM | K14: Bd | L14: Ba (or Bu)
B15: Company | C15: =AVERAGE(C2:C4) -> 0.84333333 | D15: ='NPV Calculation_Payoff'!D12 -> 10010000 | E15: ='NPV Calculation_Payoff'!D11 -> 1332910000000 | F15: =D15/E15 -> 7.5098844e-06 | G15: =F15/(F15+1) -> 7.509828e-06 | H15: =1-G15 -> 0.99999249 | I15: A | J15: ~5% | K15: 0.05 | L15: =G15*K15+H15*C15 -> 0.84332738
B17: Company | C17: Be | D17: Net Debt | E17: Market Cap | F17: D/E | G17: D/V | H17: E/V | I17: S&P Bond Rating | J17: YTM | K17: Bd | L17: Ba (or Bu)
B18: Company | C18: =IFERROR(_xlfn.FORMULATEXT(C15),C15) -> =AVERAGE(C2:C4) | D18: =IFERROR(_xlfn.FORMULATEXT(D15),D15) -> ='NPV Calculation_Payoff'!D12 | E18: =IFERROR(_xlfn.FORMULATEXT(E15),E15) -> ='NPV Calculation_Payoff'!D11 | F18: =IFERROR(_xlfn.FORMULATEXT(F15),F15) -> =D15/E15 | G18: =IFERROR(_xlfn.FORMULATEXT(G15),G15) -> =F15/(F15+1) | H18: =IFERROR(_xlfn.FORMULATEXT(H15),H15) -> =1-G15 | I18: =IFERROR(_xlfn.FORMULATEXT(I15),I15) -> A | J18: =IFERROR(_xlfn.FORMULATEXT(J15),J15) -> ~5% | ... L18: =IFERROR(_xlfn.FORMULATEXT(L15),L15) -> =G15*K15+H15*C15
B20: ITERATION: CURRENT WEIGHTS
B21: Assumptions
B22: Initial investments | D22: Weight | G22: Rf | H22: 0.0421 | N22: from investing.com
B23: Equity | C23: ='NPV Calculation_Payoff'!$D$16*D23 -> 350997.36 | D23: ='NPV Calculation_Payoff'!J6 -> 0.99999249 | G23: E(Rm) | H23: 0.0954 | N23: https://pages.stern.nyu.edu/~adamodar/New_Home_Page/datafile/histretSP.html?utm
B24: Debt | C24: ='NPV Calculation_Payoff'!$D$16*D24 -> 2.6359496 | D24: =1-D23 -> 7.509828e-06 | G24: MRP | H24: =H23-H22 -> 0.0533
B25: Equity free cash flow | C25: ='FCFE Calculations'!K55 -> 276292.13 | D25: <First year perpetuity FCFE
C27: Ba (or Bu) | D27: D/E | E27: D/V | F27: E/V | G27: Be | H27: Ke | I27: Equity value | J27: <value at FY2031
B28: Book weights | C28: =$L$5 -> 1.0199908 | D28: =C24/C23 -> 7.5098844e-06 | E28: =D28/(D28+1) -> 7.509828e-06 | F28: =1-E28 -> 0.99999249 | G28: =(C28-E28*K2)/F28 -> 1.0199981 | H28: =$H$22+G28*$H$24 -> 0.096465897 | I28: =$C$25/(H28-'FCFE Calculations'!$D$14) -> 3391506.6
B29: Iteration #1 | C29: =$L$5 -> 1.0199908 | D29: =$C$24/I28 -> 7.7722084e-07 | E29: =D29/(D29+1) -> 7.7722024e-07 | F29: =1-E29 -> 0.99999922 | G29: =(C29-E29*$K$2)/F29 -> 1.0199915 | H29: =$H$22+G29*$H$24 -> 0.096465549 | I29: =$C$25/(H29-'FCFE Calculations'!$D$14) -> 3391521.1
B30: Iteration #2 | C30: =$L$5 -> 1.0199908 | D30: =$C$24/I29 -> 7.7721752e-07 | E30: =D30/(D30+1) -> 7.7721692e-07 | F30: =1-E30 -> 0.99999922 | G30: =(C30-E30*$K$2)/F30 -> 1.0199915 | H30: =$H$22+G30*$H$24 -> 0.096465549 | I30: =$C$25/(H30-'FCFE Calculations'!$D$14) -> 3391521.1
B31: Iteration #3 | C31: =$L$5 -> 1.0199908 | D31: =$C$24/I30 -> 7.7721752e-07 | E31: =D31/(D31+1) -> 7.7721692e-07 | F31: =1-E31 -> 0.99999922 | G31: =(C31-E31*$K$2)/F31 -> 1.0199915 | H31: =$H$22+G31*$H$24 -> 0.096465549 | I31: =$C$25/(H31-'FCFE Calculations'!$D$14) -> 3391521.1
B32: Iteration #4 | C32: =$L$5 -> 1.0199908 | D32: =$C$24/I31 -> 7.7721752e-07 | E32: =D32/(D32+1) -> 7.7721692e-07 | F32: =1-E32 -> 0.99999922 | G32: =(C32-E32*$K$2)/F32 -> 1.0199915 | H32: =$H$22+G32*$H$24 -> 0.096465549 | I32: =$C$25/(H32-'FCFE Calculations'!$D$14) -> 3391521.1 | J32: =I32/(1+'FCFE Calculations'!D9)^'FCFE Calculations'!K22 -> 1951748
B33: Iteration #5 | C33: =$L$5 -> 1.0199908 | D33: =$C$24/I32 -> 7.7721752e-07 | E33: =D33/(D33+1) -> 7.7721692e-07 | F33: =1-E33 -> 0.99999922 | G33: =(C33-E33*$K$2)/F33 -> 1.0199915 | H33: =$H$22+G33*$H$24 -> 0.096465549 | I33: =$C$25/(H33-'FCFE Calculations'!$D$14) -> 3391521.1
B34: Iteration #6 | C34: =$L$5 -> 1.0199908 | D34: =$C$24/I33 -> 7.7721752e-07 | E34: =D34/(D34+1) -> 7.7721692e-07 | F34: =1-E34 -> 0.99999922 | G34: =(C34-E34*$K$2)/F34 -> 1.0199915 | H34: =$H$22+G34*$H$24 -> 0.096465549 | I34: =$C$25/(H34-'FCFE Calculations'!$D$14) -> 3391521.1
B35: Iteration #7 | C35: =$L$5 -> 1.0199908 | D35: =$C$24/I34 -> 7.7721752e-07 | E35: =D35/(D35+1) -> 7.7721692e-07 | F35: =1-E35 -> 0.99999922 | G35: =(C35-E35*$K$2)/F35 -> 1.0199915 | H35: =$H$22+G35*$H$24 -> 0.096465549 | I35: =$C$25/(H35-'FCFE Calculations'!$D$14) -> 3391521.1
B36: Iteration #8 | C36: =$L$5 -> 1.0199908 | D36: =$C$24/I35 -> 7.7721752e-07 | E36: =D36/(D36+1) -> 7.7721692e-07 | F36: =1-E36 -> 0.99999922 | G36: =(C36-E36*$K$2)/F36 -> 1.0199915 | H36: =$H$22+G36*$H$24 -> 0.096465549 | I36: =$C$25/(H36-'FCFE Calculations'!$D$14) -> 3391521.1
B37: Iteration #9 | C37: =$L$5 -> 1.0199908 | D37: =$C$24/I36 -> 7.7721752e-07 | E37: =D37/(D37+1) -> 7.7721692e-07 | F37: =1-E37 -> 0.99999922 | G37: =(C37-E37*$K$2)/F37 -> 1.0199915 | H37: =$H$22+G37*$H$24 -> 0.096465549 | I37: =$C$25/(H37-'FCFE Calculations'!$D$14) -> 3391521.1
B38: Iteration #10 | C38: =$L$5 -> 1.0199908 | D38: =$C$24/I37 -> 7.7721752e-07 | E38: =D38/(D38+1) -> 7.7721692e-07 | F38: =1-E38 -> 0.99999922 | G38: =(C38-E38*$K$2)/F38 -> 1.0199915 | H38: =$H$22+G38*$H$24 -> 0.096465549 | I38: =$C$25/(H38-'FCFE Calculations'!$D$14) -> 3391521.1
B40: ITERATION: INVERSE WEIGHTS
B41: Assumptions
B42: Initial investments | D42: Inverse Weights | G42: Rf | H42: =H22 -> 0.0421
B43: Equity | C43: ='NPV Calculation_Payoff'!$D$16*D43 -> 2.6359496 | D43: ='NPV Calculation_Payoff'!J7 -> 7.509828e-06 | G43: E(Rm) | H43: 0.0954
B44: Debt | C44: ='NPV Calculation_Payoff'!$D$16*D44 -> 350997.36 | D44: =1-D43 -> 0.99999249 | G44: MRP | H44: =H43-H42 -> 0.0533
B45: Equity free cash flow | C45: ='FCFE Calculations'!K55 -> 276292.13 | D45: <First year perpetuity FCFE
C47: Ba (or Bu) | D47: D/E | E47: D/V | F47: E/V | G47: Be | H47: Ke | I47: Equity value | J47: <value at FY2031
B48: Book weights | C48: =$L$5 -> 1.0199908 | D48: =C44/C43 -> 133157.84 | E48: =D48/(D48+1) -> 0.99999249 | F48: =1-E48 -> 7.509828e-06 | G48: =(C48-E48*$K$2)/F48 -> 129162.9 | H48: =$H$42+G48*$H$44 -> 6884.4247 | I48: =$C$45/(H48-'FCFE Calculations'!$D$14) -> 40.133017
B49: Iteration #1 | C49: =$L$5 -> 1.0199908 | D49: =$C$44/I48 -> 8745.8505 | E49: =D49/(D49+1) -> 0.99988567 | F49: =1-E49 -> 0.00011432687 | G49: =(C49-E49*$K$2)/F49 -> 8484.4144 | H49: =$H$42+G49*$H$44 -> 452.26139 | I49: =$C$45/(H49-'FCFE Calculations'!$D$14) -> 610.93275
B50: Iteration #2 | C50: =$L$5 -> 1.0199908 | D50: =$C$44/I49 -> 574.52701 | E50: =D50/(D50+1) -> 0.99826246 | F50: =1-E50 -> 0.0017375379 | G50: =(C50-E50*$K$2)/F50 -> 558.3059 | H50: =$H$42+G50*$H$44 -> 29.799804 | I50: =$C$45/(H50-'FCFE Calculations'!$D$14) -> 9276.2782
B51: Iteration #3 | C51: =$L$5 -> 1.0199908 | D51: =$C$44/I50 -> 37.838167 | E51: =D51/(D51+1) -> 0.97425213 | F51: =1-E51 -> 0.025747868 | G51: =(C51-E51*$K$2)/F51 -> 37.722665 | H51: =$H$42+G51*$H$44 -> 2.052718 | I51: =$C$45/(H51-'FCFE Calculations'!$D$14) -> 135588.99
B52: Iteration #4 | C52: =$L$5 -> 1.0199908 | D52: =$C$44/I51 -> 2.5886863 | E52: =D52/(D52+1) -> 0.7213465 | F52: =1-E52 -> 0.2786535 | G52: =(C52-E52*$K$2)/F52 -> 3.5309927 | H52: =$H$42+G52*$H$44 -> 0.23030191 | I52: =$C$45/(H52-'FCFE Calculations'!$D$14) -> 1283277.7 | J52: =I52-I32 -> -2108243.4
B53: Iteration #5 | C53: =$L$5 -> 1.0199908 | D53: =$C$44/I52 -> 0.27351631 | E53: =D53/(D53+1) -> 0.21477252 | F53: =1-E53 -> 0.78522748 | G53: =(C53-E53*$K$2)/F53 -> 1.2852991 | H53: =$H$42+G53*$H$44 -> 0.11060644 | I53: =$C$45/(H53-'FCFE Calculations'!$D$14) -> 2889890.3
B54: Iteration #6 | C54: =$L$5 -> 1.0199908 | D54: =$C$44/I53 -> 0.12145698 | E54: =D54/(D54+1) -> 0.10830285 | F54: =1-E54 -> 0.89169715 | G54: =(C54-E54*$K$2)/F54 -> 1.1378029 | H54: =$H$42+G54*$H$44 -> 0.1027449 | I54: =$C$45/(H54-'FCFE Calculations'!$D$14) -> 3148811.4
B55: Iteration #7 | C55: =$L$5 -> 1.0199908 | D55: =$C$44/I54 -> 0.1114698 | E55: =D55/(D55+1) -> 0.10029044 | F55: =1-E55 -> 0.89970956 | G55: =(C55-E55*$K$2)/F55 -> 1.1281155 | H55: =$H$42+G55*$H$44 -> 0.10222855 | I55: =$C$45/(H55-'FCFE Calculations'!$D$14) -> 3167450.5
B56: Iteration #8 | C56: =$L$5 -> 1.0199908 | D56: =$C$44/I55 -> 0.11081384 | E56: =D56/(D56+1) -> 0.099759148 | F56: =1-E56 -> 0.90024085 | G56: =(C56-E56*$K$2)/F56 -> 1.1274792 | H56: =$H$42+G56*$H$44 -> 0.10219464 | I56: =$C$45/(H56-'FCFE Calculations'!$D$14) -> 3168682.5
B57: Iteration #9 | C57: =$L$5 -> 1.0199908 | D57: =$C$44/I56 -> 0.11077076 | E57: =D57/(D57+1) -> 0.099724231 | F57: =1-E57 -> 0.90027577 | G57: =(C57-E57*$K$2)/F57 -> 1.1274374 | H57: =$H$42+G57*$H$44 -> 0.10219241 | I57: =$C$45/(H57-'FCFE Calculations'!$D$14) -> 3168763.4
B58: Iteration #10 | C58: =$L$5 -> 1.0199908 | D58: =$C$44/I57 -> 0.11076793 | E58: =D58/(D58+1) -> 0.099721938 | F58: =1-E58 -> 0.90027806 | G58: =(C58-E58*$K$2)/F58 -> 1.1274347 | H58: =$H$42+G58*$H$44 -> 0.10219227 | I58: =$C$45/(H58-'FCFE Calculations'!$D$14) -> 3168768.7

Sheet FCFE Calculations
B2: DCF Model
B4: Assumptions | I4: Gross Margin | J4: =Assumptions!B6 -> 0.36
B5: Tax Rate | D5: =Assumptions!B9 -> 0.2284 | I5: Revenues from Investment | J5: =Assumptions!B3 -> 695000
B6: Equity Beta | D6: =('Ba Calculation'!L5-('Ba Calculation'!K3*J7))/J6 -> 1.0199981 | I6: We | J6: =D11/SUM($D$11:$D$12) -> 0.99999249
B7: Market risk premium | D7: ='Ba Calculation'!H24 -> 0.0533 | I7: Wd | J7: =D12/SUM($D$11:$D$12) -> 7.509828e-06
B8: Risk free rate | D8: ='Ba Calculation'!H22 -> 0.0421 | I8: Salvage Value | J8: 0
B9: Cost of equity | D9: =D8+D6*D7 -> 0.096465897
B10: Cost of debt | D10: ='Bond Ratings'!E4 -> 0.0482 | E10: Taking industry average
B11: Market value of equity | D11: =AVERAGE('Ba Calculation'!E2:E4) -> 1332910000000 | E11: Taking industry average
B12: Net debt | D12: =AVERAGE('Ba Calculation'!D2:D4) -> 10010000 | E12: Taking industry average
B13: WACC | D13: =D12/(D12+D11)*D10*(1-D5)+(D11/(D12+D11))*D9 -> 0.096465452 | E13: =J6*D9+J7*D10*(1-D5) -> 0.096465452
B14: Perpetual Growth Rate | D14: =Assumptions!B5 -> 0.015
B15: CAGR | D15: =Assumptions!B4 -> 0.07
B16: Upfront investment | D16: ='Cost Data'!G22 -> 351000
B17: Today's date | D17: 46387
B18: Fiscal Year End | D18: 46660
B19: Option: Continue | K19: Perpetuity Begins
B20: Discounted Cash Flow | D20: Startup | E20: =YEAR(E21) -> 2027 | F20: =YEAR(F21) -> 2028 | G20: =YEAR(G21) -> 2029 | H20: =YEAR(H21) -> 2030 | I20: =YEAR(I21) -> 2031 | J20: =YEAR(J21) -> 2032 | K20: =YEAR(K21) -> 2033 | L20: =YEAR(L21) -> 2034 | M20: =YEAR(M21) -> 2035
B21: Date | D21: =D17 -> 46387 | E21: =DATE(YEAR($D$18)+E22,9,30) -> 46660 | F21: =DATE(YEAR($D$18)+F22,9,30) -> 47026 | G21: =DATE(YEAR($D$18)+G22,9,30) -> 47391 | H21: =DATE(YEAR($D$18)+H22,9,30) -> 47756 | I21: =DATE(YEAR($D$18)+I22,9,30) -> 48121 | J21: =DATE(YEAR($D$18)+J22,9,30) -> 48487 | K21: =DATE(YEAR($D$18)+K22,9,30) -> 48852 | L21: =DATE(YEAR($D$18)+L22,9,30) -> 49217 | M21: =DATE(YEAR($D$18)+M22,9,30) -> 49582
B22: Time Periods | E22: 0 | F22: =E22+1 -> 1 | G22: =F22+1 -> 2 | H22: =G22+1 -> 3 | I22: =H22+1 -> 4 | J22: =I22+1 -> 5 | K22: =J22+1 -> 6 | L22: =K22+1 -> 7 | M22: =L22+1 -> 8
B23: Year Fraction | E23: =YEARFRAC(D21,E21) -> 0.75 | F23: =YEARFRAC(E21,F21) -> 1 | G23: =YEARFRAC(F21,G21) -> 1 | H23: =YEARFRAC(G21,H21) -> 1 | I23: =YEARFRAC(H21,I21) -> 1 | J23: =YEARFRAC(I21,J21) -> 1
B24: Revenue | E24: =J5 -> 695000 | F24: =E24*(1+$D$15) -> 743650 | G24: =F24*(1+$D$15) -> 795705.5 | H24: =G24*(1+$D$15) -> 851404.89 | I24: =H24*(1+$D$15) -> 911003.23 | J24: =I24*(1+$D$15) -> 974773.45 | K24: =J24*(1+$D$14) -> 989395.05 | L24: =K24*(1+$D$14) -> 1004236 | M24: =L24*(1+$D$14) -> 1019299.5
B25: Expenses | E25: =(1-$J$4)*E24 -> 444800 | F25: =(1-$J$4)*F24 -> 475936 | G25: =(1-$J$4)*G24 -> 509251.52 | H25: =(1-$J$4)*H24 -> 544899.13 | I25: =(1-$J$4)*I24 -> 583042.07 | J25: =(1-$J$4)*J24 -> 623855.01 | K25: =(1-$J$4)*K24 -> 633212.83 | L25: =(1-$J$4)*L24 -> 642711.03 | M25: =(1-$J$4)*M24 -> 652351.69
B26: Depreciation | E26: 0 | F26: 0 | G26: 0 | H26: 0 | I26: 0 | J26: 0 | K26: 0 | L26: 0 | M26: 0
B27: EBIT | E27: =E24-E25-E26 -> 250200 | F27: =F24-F25-F26 -> 267714 | G27: =G24-G25-G26 -> 286453.98 | H27: =H24-H25-H26 -> 306505.76 | I27: =I24-I25-I26 -> 327961.16 | J27: =J24-J25-J26 -> 350918.44 | K27: =K24-K25-K26 -> 356182.22 | L27: =L24-L25-L26 -> 361524.95 | M27: =M24-M25-M26 -> 366947.83
B28: Less: Taxes | E28: =-E27*$D$5 -> -57145.68 | F28: =-F27*$D$5 -> -61145.878 | G28: =-G27*$D$5 -> -65426.089 | H28: =-H27*$D$5 -> -70005.915 | I28: =-I27*$D$5 -> -74906.329 | J28: =-J27*$D$5 -> -80149.772 | K28: =-K27*$D$5 -> -81352.019 | L28: =-L27*$D$5 -> -82572.299 | M28: =-M27*$D$5 -> -83810.884
B29: Plus: D&A | E29: =E26 -> 0 | F29: =F26 -> 0 | G29: =G26 -> 0 | H29: =H26 -> 0 | I29: =I26 -> 0 | J29: =J26 -> 0 | K29: =K26 -> 0 | L29: =L26 -> 0 | M29: =M26 -> 0
B30: Plus: Inc in deferred taxes | E30: 0 | F30: 0 | G30: 0 | H30: 0 | I30: 0 | J30: 0 | K30: 0 | L30: 0 | M30: 0
B31: Less: Capex | D31: =-D16 -> -351000
B32: Less: Changes in NWC | E32: =-E44 -> 69515.886 | F32: =-F44 -> 4866.112 | G32: =-G44 -> 5206.7398 | H32: =-H44 -> 5571.2116 | I32: =-I44 -> 5961.1964 | J32: =-J44 -> 6378.4802 | K32: =-K44 -> 1462.4944 | L32: =-L44 -> 1484.4318 | M32: =-M44 -> 1506.6983
B33: Unlevered FCF | D33: =D27+SUM(D28:D32) -> -351000 | E33: =E27+SUM(E28:E32) -> 262570.21 | F33: =F27+SUM(F28:F32) -> 211434.23 | G33: =G27+SUM(G28:G32) -> 226234.63 | H33: =H27+SUM(H28:H32) -> 242071.05 | I33: =I27+SUM(I28:I32) -> 259016.03 | J33: =J27+SUM(J28:J32)+J34 -> 3668679.2 | K33: =K27+SUM(K28:K32) -> 276292.7 | L33: =L27+SUM(L28:L32) -> 280437.09 | M33: =M27+SUM(M28:M32) -> 284643.64
B34: Terminal Value | J34: =K33/(D13-D14) -> 3391532.1 | L34: =M33/(D13-D14) -> 3494041.1
I35: FCFF_31 Only > | J35: =J27+SUM(J28:J32) -> 277147.15 | L35: =SUM(L33:L34) -> 3774478.2 | M35: <total fcf 33
B36: Net Present Value of FCFF | D36: =XNPV(D13,D33:J33,D21:J21) -> 2747998.8 | E36: =NPV(D13,E33:J33)+D33 -> 2678129
B38: Net Working Capital Forecast | D38: Startup | E38: 2026 | F38: 2027 | G38: 2028 | H38: 2029 | I38: 2030 | J38: 2031 | K38: 2032 | L38: 2032 | M38: 2032
B39: Cash Requirements | D39: 0 | E39: 0 | F39: 0 | G39: 0 | H39: 0 | I39: 0 | J39: 0 | K39: 0 | L39: 0 | M39: 0
B40: PLUS: Inventory | D40: 0 | E40: 0 | F40: 0 | G40: 0 | H40: 0 | I40: 0 | J40: 0 | K40: 0 | L40: 0 | M40: 0
B41: PLUS: Receivables @ x% of Sales | D41: 0 | E41: =E24*$C$46 -> 55138.261 | F41: =F24*$C$46 -> 58997.94 | G41: =G24*$C$46 -> 63127.796 | H41: =H24*$C$46 -> 67546.741 | I41: =I24*$C$46 -> 72275.013 | J41: =J24*$C$46 -> 77334.264 | K41: =K24*$C$46 -> 78494.278 | L41: =L24*$C$46 -> 79671.692 | M41: =M24*$C$46 -> 80866.768
B42: LESS: Payables @ x% of COGs | D42: 0 | E42: =-E25*$C$47 -> -124654.15 | F42: =-F25*$C$47 -> -133379.94 | G42: =-G25*$C$47 -> -142716.53 | H42: =-H25*$C$47 -> -152706.69 | I42: =-I25*$C$47 -> -163396.16 | J42: =-J25*$C$47 -> -174833.89 | K42: =-K25*$C$47 -> -177456.4 | L42: =-L25*$C$47 -> -180118.24 | M42: =-M25*$C$47 -> -182820.02
B43: Net Working Capital | D43: =SUM(D39:D42) -> 0 | E43: =SUM(E39:E42) -> -69515.886 | F43: =SUM(F39:F42) -> -74381.997 | G43: =SUM(G39:G42) -> -79588.737 | H43: =SUM(H39:H42) -> -85159.949 | I43: =SUM(I39:I42) -> -91121.145 | J43: =SUM(J39:J42) -> -97499.626 | K43: =SUM(K39:K42) -> -98962.12 | ... M43: =SUM(M39:M42) -> -101953.25
B44: Increases in NWC | E44: =E43-D43 -> -69515.886 | F44: =F43-E43 -> -4866.112 | G44: =G43-F43 -> -5206.7398 | H44: =H43-G43 -> -5571.2116 | I44: =I43-H43 -> -5961.1964 | J44: =J43-I43 -> -6378.4802 | K44: =K43-J43 -> -1462.4944 | L44: =L43-K43 -> -1484.4318 | M44: =M43-L43 -> -1506.6983
B46: Receivables % of Sales | C46: =AVERAGE('Average Industry Growth'!B47:B49) -> 0.079335628
B47: Payables % of COGS | C47: =AVERAGE('Average Industry Growth'!B62:B64) -> 0.28024763
B49: Levered Value @ WACC | D49: =(E33+E49)/(1+$D$13) -> 3029129 | E49: =(F33+F49)/(1+$D$13) -> 3058765 | F49: =(G33+G49)/(1+$D$13) -> 3142396 | G49: =(H33+H49)/(1+$D$13) -> 3219294 | H49: =(I33+I49)/(1+$D$13) -> 3287773.6 | I49: =(J35+J49)/(1+$D$13) -> 3345914.1 | J49: =(K33+K49)/(1+$D$13) -> 3391532.1 | K49: =L35/(1+$D$13) -> 3442405.1
B50: Debt Capacity @ Wd | D50: =D49*$J$7 -> 22.748237 | E50: =E49*$J$7 -> 22.970799 | F50: =F49*$J$7 -> 23.598853 | G50: =G49*$J$7 -> 24.176344 | H50: =H49*$J$7 -> 24.690614 | I50: =I49*$J$7 -> 25.127239 | J50: =J49*$J$7 -> 25.469823 | K50: =K49*$J$7 -> 25.85187
B53: LESS: After-Tax Interest Expense | E53: =-D50*$D$10*(1-$D$5) -> -0.84603243 | F53: =-E50*$D$10*(1-$D$5) -> -0.85430976 | G53: =-F50*$D$10*(1-$D$5) -> -0.87766778 | H53: =-G50*$D$10*(1-$D$5) -> -0.89914531 | I53: =-H50*$D$10*(1-$D$5) -> -0.91827159 | J53: =-I50*$D$10*(1-$D$5) -> -0.93451018 | K53: =-J50*$D$10*(1-$D$5) -> -0.94725123 | L53: =-K50*$D$10*(1-$D$5) -> -0.96146
B54: PLUS: Net Borrowing | D54: =D50 -> 22.748237 | E54: =E50-D50 -> 0.22256193 | F54: =F50-E50 -> 0.62805382 | G54: =G50-F50 -> 0.57749088 | H54: =H50-G50 -> 0.51426998 | I54: =I50-H50 -> 0.43662543 | J54: =J50-I50 -> 0.34258309 | K54: =K50-J50 -> 0.38204734 | L54: =L50-K50 -> -25.85187
B55: Equity/Levered FCF | D55: =D33+SUM(D53:D54) -> -350977.25 | E55: =E33+SUM(E53:E54) -> 262569.58 | F55: =F33+SUM(F53:F54) -> 211434.01 | G55: =G33+SUM(G53:G54) -> 226234.33 | H55: =H33+SUM(H53:H54) -> 242070.67 | I55: =I33+SUM(I53:I54) -> 259015.55 | J55: =J35+SUM(J53:J54) -> 277146.56 | K55: =K33+SUM(K53:K54) -> 276292.13 | L55: =L35+SUM(L53:L54) -> 3774451.4
B57: NPV of FCFE | C57: =XNPV(D9,D55:L55,D21:L21) -> 2747998.6 | D57: =NPV(D9,E55:L55)+D55 -> 2678129
C58: =C57-D36 -> -0.21177216 | D58: =D57-E36 -> 0 | E58: <Should be 0 | J58: Re | K58: Ke
B59: Example from textbook | C59: Year 0 | D59: Year 1 | E59: Year 2 | F59: Year 3 | G59: Year 4 | I59: Equity Value of Perp @ T = 2031 | J59: =K55/(D9-D14) -> 3391506.6 | K59: =K55/('Ba Calculation'!H32-D14) -> 3391521.1
B60: Unlevered FCF | C60: -29 | D60: 21 | E60: 21 | F60: 21 | G60: 21 | I60: Equity Value of Perp @ T = 2025 | J60: =J59/(1+D9)^J22 -> 2140016 | K60: =J59/(1+'Ba Calculation'!H32)^J22 -> 2140019.4
B62: Levered Value @7.25% WACC | C62: =(D60+D62)/(1.0725) -> 70.731823 | D62: =(E60+E62)/(1.0725) -> 54.85988 | E62: =(F60+F62)/(1.0725) -> 37.837221 | F62: =G60/(1.0725) -> 19.58042
B63: Debt Capacity @ d=50% | C63: =C62*0.5 -> 35.365911 | D63: =D62*0.5 -> 27.42994 | E63: =E62*0.5 -> 18.918611 | F63: =F62*0.5 -> 9.7902098
B65: LESS After Tax Expense, @ t = 25% and cost of d = 6% | D65: =-C63*0.06*(1-0.25) -> -1.591466 | E65: =-D63*0.06*(1-0.25) -> -1.2343473 | F65: =-E63*0.06*(1-0.25) -> -0.85133747 | G65: =-F63*0.06*(1-0.25) -> -0.44055944
B66: PLUS: Net Borrowing | C66: =C63 -> 35.365911 | D66: =D63-C63 -> -7.9359714 | E66: =E63-D63 -> -8.5113294 | F66: =F63-E63 -> -9.1284007 | G66: =G63-F63 -> -9.7902098
B67: FCFE | C67: =C60+SUM(C65:C66) -> 6.3659113 | D67: =D60+SUM(D65:D66) -> 11.472563 | E67: =E60+SUM(E65:E66) -> 11.254323 | F67: =F60+SUM(F65:F66) -> 11.020262 | G67: =G60+SUM(G65:G66) -> 10.769231
B69: NPV of FCFE | C69: =NPV(0.1,D67:G67)+C67 -> 41.731823
B70: NPV of FCFF | C70: =NPV(0.0725,D60:G60)+C60 -> 41.731823

Sheet NPV Calculation_Payoff
B2: DCF Model
B4: Assumptions | I4: Gross Margin | J4: =Assumptions!B6 -> 0.36
B5: Tax Rate | D5: =Assumptions!B9 -> 0.2284 | I5: Revenues from Investment | J5: =Assumptions!B3 -> 695000
B6: Equity Beta | D6: =('Ba Calculation'!L5-('Ba Calculation'!K3*J7))/J6 -> 1.0199981 | I6: We | J6: =D11/SUM($D$11:$D$12) -> 0.99999249
B7: Market risk premium | D7: ='Ba Calculation'!H24 -> 0.0533 | I7: Wd | J7: =D12/SUM($D$11:$D$12) -> 7.509828e-06
B8: Risk free rate | D8: ='Ba Calculation'!H22 -> 0.0421 | I8: Salvage Value | J8: 0
B9: Cost of equity | D9: =D8+D6*D7 -> 0.096465897
B10: Cost of debt | D10: ='FCFE Calculations'!D10 -> 0.0482 | E10: https://ycharts.com/indicators/us_corporate_a_effective_yield
B11: Market value of equity | D11: ='FCFE Calculations'!D11 -> 1332910000000 | E11: https://finance.yahoo.com/quote/ROK/
B12: Net debt | D12: ='FCFE Calculations'!D12 -> 10010000 | E12: https://finance.yahoo.com/quote/ROK/balance-sheet/
B13: WACC | D13: =D12/(D12+D11)*D10*(1-D5)+(D11/(D12+D11))*D9 -> 0.096465452 | E13: =J6*D9+J7*D10*(1-D5) -> 0.096465452
B14: Perpetual Growth Rate | D14: =Assumptions!B5 -> 0.015
B15: CAGR | D15: =Assumptions!B4 -> 0.07
B16: Upfront investment | D16: ='Cost Data'!G22 -> 351000
B17: Today's date | D17: 46387
B18: Fiscal Year End | D18: 46660
B19: Option: Continue | N19: Option: Abandon in FY27
B20: Discounted Cash Flow | D20: Startup | E20: =YEAR(E21) -> 2027 | F20: =YEAR(F21) -> 2028 | G20: =YEAR(G21) -> 2029 | H20: =YEAR(H21) -> 2030 | I20: =YEAR(I21) -> 2031 | J20: =YEAR(J21) -> 2032 | N20: Discounted Cash Flow | P20: Startup | Q20: =YEAR(Q21) -> 2027 | R20: =YEAR(R21) -> 2028 | S20: =YEAR(S21) -> 2029 | T20: =YEAR(T21) -> 2030 | U20: =YEAR(U21) -> 2031 | V20: =YEAR(V21) -> 2032
B21: Date | D21: =D17 -> 46387 | E21: =DATE(YEAR($D$18)+E22,9,30) -> 46660 | F21: =DATE(YEAR($D$18)+F22,9,30) -> 47026 | G21: =DATE(YEAR($D$18)+G22,9,30) -> 47391 | H21: =DATE(YEAR($D$18)+H22,9,30) -> 47756 | I21: =DATE(YEAR($D$18)+I22,9,30) -> 48121 | J21: =DATE(YEAR($D$18)+J22,9,30) -> 48487 | K21: =DATE(YEAR($D$18)+K22,9,30) -> 48852 | N21: Date | P21: =D17 -> 46387 | Q21: =DATE(YEAR($D$18)+Q22,9,30) -> 46660 | R21: =DATE(YEAR($D$18)+R22,9,30) -> 47026 | S21: =DATE(YEAR($D$18)+S22,9,30) -> 47391 | T21: =DATE(YEAR($D$18)+T22,9,30) -> 47756 | U21: =DATE(YEAR($D$18)+U22,9,30) -> 48121 | V21: =DATE(YEAR($D$18)+V22,9,30) -> 48487
B22: Time Periods | E22: 0 | F22: =E22+1 -> 1 | G22: =F22+1 -> 2 | H22: =G22+1 -> 3 | I22: =H22+1 -> 4 | J22: =I22+1 -> 5 | K22: =J22+1 -> 6 | N22: Time Periods | Q22: 0 | R22: =Q22+1 -> 1 | S22: =R22+1 -> 2 | T22: =S22+1 -> 3 | U22: =T22+1 -> 4 | V22: 5
B23: Year Fraction | E23: =YEARFRAC(D21,E21) -> 0.75 | F23: =YEARFRAC(E21,F21) -> 1 | G23: =YEARFRAC(F21,G21) -> 1 | H23: =YEARFRAC(G21,H21) -> 1 | I23: =YEARFRAC(H21,I21) -> 1 | J23: =YEARFRAC(I21,J21) -> 1 | N23: Year Fraction | Q23: =YEARFRAC(P21,Q21) -> 0.75 | R23: =YEARFRAC(Q21,R21) -> 1 | S23: =YEARFRAC(R21,S21) -> 1 | T23: =YEARFRAC(S21,T21) -> 1 | U23: =YEARFRAC(T21,U21) -> 1 | V23: =YEARFRAC(U21,V21) -> 1
B24: Revenue | E24: =J5 -> 695000 | F24: =E24*(1+$D$15) -> 743650 | G24: =F24*(1+$D$15) -> 795705.5 | H24: =G24*(1+$D$15) -> 851404.89 | I24: =H24*(1+$D$15) -> 911003.23 | J24: =I24*(1+$D$15) -> 974773.45 | K24: =J24*(1+D14) -> 989395.05 | N24: Revenue | Q24: =J5 -> 695000 | R24: =0+J8 -> 0 | S24: 0 | T24: 0 | U24: 0 | V24: 0 | W24: 0
B25: Expenses | E25: =(1-$J$4)*E24 -> 444800 | F25: =(1-$J$4)*F24 -> 475936 | G25: =(1-$J$4)*G24 -> 509251.52 | H25: =(1-$J$4)*H24 -> 544899.13 | I25: =(1-$J$4)*I24 -> 583042.07 | J25: =(1-$J$4)*J24 -> 623855.01 | K25: =(1-$J$4)*K24 -> 633212.83 | N25: Expenses | Q25: =(1-$J$4)*Q24 -> 444800 | R25: 0 | S25: 0 | T25: 0 | U25: 0 | V25: 0 | W25: 0
B26: Depreciation | E26: 0 | F26: 0 | G26: 0 | H26: 0 | I26: 0 | J26: 0 | K26: 0 | N26: Depreciation | Q26: 0 | R26: 0 | S26: 0 | T26: 0 | U26: 0 | V26: 0 | W26: 0
B27: EBIT | E27: =E24-E25-E26 -> 250200 | F27: =F24-F25-F26 -> 267714 | G27: =G24-G25-G26 -> 286453.98 | H27: =H24-H25-H26 -> 306505.76 | I27: =I24-I25-I26 -> 327961.16 | J27: =J24-J25-J26 -> 350918.44 | K27: =K24-K25-K26 -> 356182.22 | N27: EBIT | Q27: =Q24-Q25-Q26 -> 250200 | R27: =R24-R25-R26 -> 0 | S27: =S24-S25-S26 -> 0 | T27: =T24-T25-T26 -> 0 | U27: =U24-U25-U26 -> 0 | V27: =V24-V25-V26 -> 0 | W27: =W24-W25-W26 -> 0
B28: Less: Taxes | E28: =-E27*$D$5 -> -57145.68 | F28: =-F27*$D$5 -> -61145.878 | G28: =-G27*$D$5 -> -65426.089 | H28: =-H27*$D$5 -> -70005.915 | I28: =-I27*$D$5 -> -74906.329 | J28: =-J27*$D$5 -> -80149.772 | K28: =-K27*$D$5 -> -81352.019 | N28: Less: Taxes | Q28: =-Q27*$D$5 -> -57145.68 | R28: =-R27*$D$5 -> 0 | S28: =-S27*$D$5 -> 0 | T28: =-T27*$D$5 -> 0 | U28: =-U27*$D$5 -> 0 | V28: =-V27*$D$5 -> 0 | W28: =-W27*$D$5 -> 0
B29: Plus: D&A | E29: =E26 -> 0 | F29: =F26 -> 0 | G29: =G26 -> 0 | H29: =H26 -> 0 | I29: =I26 -> 0 | J29: =J26 -> 0 | K29: =K26 -> 0 | N29: Plus: D&A | Q29: =Q26 -> 0 | R29: =R26 -> 0 | S29: =S26 -> 0 | T29: =T26 -> 0 | U29: =U26 -> 0 | V29: =V26 -> 0 | W29: =W26 -> 0
B30: Plus: Inc in deferred taxes | E30: 0 | F30: 0 | G30: 0 | H30: 0 | I30: 0 | J30: 0 | K30: 0 | N30: Plus: Inc in deferred taxes | Q30: 0 | R30: 0 | S30: 0 | T30: 0 | U30: 0 | V30: 0 | W30: 0
B31: Less: Capex | D31: =-D16 -> -351000 | N31: Less: Capex | P31: =-D16 -> -351000
B32: Less: Changes in NWC | E32: =-E44 -> 69515.886 | F32: =-F44 -> 4866.112 | G32: =-G44 -> 5206.7398 | H32: =-H44 -> 5571.2116 | I32: =-I44 -> 5961.1964 | J32: =-J44 -> 6378.4802 | K32: =-K44 -> 1462.4944 | N32: Less: Changes in NWC | Q32: =-Q44 -> 69515.886 | R32: =-R44 -> -69515.886 | S32: =-S44 -> 0 | T32: =-T44 -> 0 | U32: =-U44 -> 0 | V32: =-V44 -> 0 | W32: =-W44 -> 0
B33: Unlevered FCF | D33: =D27+SUM(D28:D32) -> -351000 | E33: =E27+SUM(E28:E32) -> 262570.21 | F33: =F27+SUM(F28:F32) -> 211434.23 | G33: =G27+SUM(G28:G32) -> 226234.63 | H33: =H27+SUM(H28:H32) -> 242071.05 | I33: =I27+SUM(I28:I32) -> 259016.03 | J33: =J27+SUM(J28:J32)+J34 -> 3668679.2 | K33: =K27+SUM(K28:K32) -> 276292.7 | N33: Unlevered FCF | P33: =P27+SUM(P28:P32) -> -351000 | Q33: =Q27+SUM(Q28:Q32) -> 262570.21 | R33: =R27+SUM(R28:R32) -> -69515.886 | S33: =S27+SUM(S28:S32) -> 0 | T33: =T27+SUM(T28:T32) -> 0 | U33: =U27+SUM(U28:U32) -> 0 | V33: =V27+SUM(V28:V32)+V34 -> 0 | W33: =W27+SUM(W28:W32) -> 0
B34: Terminal Value | J34: =K33/(D13-D14) -> 3391532.1 | N34: Terminal Value | V34: =W33/(D13-D14) -> 0
I35: FCFF_31 Only > | J35: =J27+SUM(J28:J32) -> 277147.15
B36: Net Present Value of FCFF | D36: =XNPV(D13,D33:J33,D21:J21) -> 2747998.8 | E36: =NPV(D13,E33:J33)+D33 -> 2678129 | N36: Net Present Value | P36: =XNPV(D13,P33:V33,P21:V21) -> -165071.8
B38: Net Working Capital Forecast | D38: Startup | E38: 2026 | F38: 2027 | G38: 2028 | H38: 2029 | I38: 2030 | J38: 2031 | K38: 2032 | N38: Net Working Capital Forecast
B39: Cash Requirements | D39: 0 | E39: 0 | F39: 0 | G39: 0 | H39: 0 | I39: 0 | J39: 0 | K39: 0 | N39: Cash Requirements | P39: 0 | Q39: 0 | R39: 0 | S39: 0 | T39: 0 | U39: 0 | V39: 0 | W39: 0
B40: PLUS: Inventory | D40: 0 | E40: 0 | F40: 0 | G40: 0 | H40: 0 | I40: 0 | J40: 0 | K40: 0 | N40: PLUS: Inventory | P40: 0 | Q40: 0 | R40: 0 | S40: 0 | T40: 0 | U40: 0 | V40: 0 | W40: 0
B41: PLUS: Receivables @ x% of Sales | D41: 0 | E41: =E24*$C$46 -> 55138.261 | F41: =F24*$C$46 -> 58997.94 | G41: =G24*$C$46 -> 63127.796 | H41: =H24*$C$46 -> 67546.741 | I41: =I24*$C$46 -> 72275.013 | J41: =J24*$C$46 -> 77334.264 | K41: =K24*$C$46 -> 78494.278 | N41: PLUS: Receivables @ x% of Sales | P41: 0 | Q41: =Q24*$O$46 -> 55138.261 | R41: =R24*$O$46 -> 0 | S41: =S24*$O$46 -> 0 | T41: =T24*$O$46 -> 0 | U41: =U24*$O$46 -> 0 | V41: =V24*$O$46 -> 0 | W41: =W24*$O$46 -> 0
B42: LESS: Payables @ x% of COGs | D42: 0 | E42: =-E25*$C$47 -> -124654.15 | F42: =-F25*$C$47 -> -133379.94 | G42: =-G25*$C$47 -> -142716.53 | H42: =-H25*$C$47 -> -152706.69 | I42: =-I25*$C$47 -> -163396.16 | J42: =-J25*$C$47 -> -174833.89 | K42: =-K25*$C$47 -> -177456.4 | N42: LESS: Payables @ x% of COGs | P42: 0 | Q42: =-Q25*$O$47 -> -124654.15 | R42: =-R25*$O$47 -> 0 | S42: =-S25*$O$47 -> 0 | T42: =-T25*$O$47 -> 0 | U42: =-U25*$O$47 -> 0 | V42: =-V25*$O$47 -> 0 | W42: =-W25*$O$47 -> 0
B43: Net Working Capital | D43: =SUM(D39:D42) -> 0 | E43: =SUM(E39:E42) -> -69515.886 | F43: =SUM(F39:F42) -> -74381.997 | G43: =SUM(G39:G42) -> -79588.737 | H43: =SUM(H39:H42) -> -85159.949 | I43: =SUM(I39:I42) -> -91121.145 | J43: =SUM(J39:J42) -> -97499.626 | K43: =SUM(K39:K42) -> -98962.12 | N43: Net Working Capital | P43: =SUM(P39:P42) -> 0 | Q43: =SUM(Q39:Q42) -> -69515.886 | R43: =SUM(R39:R42) -> 0 | S43: =SUM(S39:S42) -> 0 | T43: =SUM(T39:T42) -> 0 | U43: =SUM(U39:U42) -> 0 | V43: =SUM(V39:V42) -> 0 | W43: =SUM(W39:W42) -> 0
B44: Increases in NWC | E44: =E43-D43 -> -69515.886 | F44: =F43-E43 -> -4866.112 | G44: =G43-F43 -> -5206.7398 | H44: =H43-G43 -> -5571.2116 | I44: =I43-H43 -> -5961.1964 | J44: =J43-I43 -> -6378.4802 | K44: =K43-J43 -> -1462.4944 | N44: Increases in NWC | Q44: =Q43-P43 -> -69515.886 | R44: =R43-Q43 -> 69515.886 | S44: =S43-R43 -> 0 | T44: =T43-S43 -> 0 | U44: =U43-T43 -> 0 | V44: =V43-U43 -> 0 | W44: =W43-V43 -> 0
B46: Receivables % of Sales | C46: ='FCFE Calculations'!C46 -> 0.079335628 | N46: Receivables % of Sales | O46: ='FCFE Calculations'!C46 -> 0.079335628
B47: Payables % of COGS | C47: ='FCFE Calculations'!C47 -> 0.28024763 | N47: Payables % of COGS | O47: ='FCFE Calculations'!C47 -> 0.28024763
B49: Levered Value @ WACC | D49: =(E33+E49)/(1+$D$13) -> 3029129 | E49: =(F33+F49)/(1+$D$13) -> 3058765 | F49: =(G33+G49)/(1+$D$13) -> 3142396 | G49: =(H33+H49)/(1+$D$13) -> 3219294 | H49: =(I33+I49)/(1+$D$13) -> 3287773.6 | I49: =J33/(1+$D$13) -> 3345914.1
B50: Debt Capacity @ Wd | D50: =D49*$J$7 -> 22.748237 | E50: =E49*$J$7 -> 22.970799 | F50: =F49*$J$7 -> 23.598853 | G50: =G49*$J$7 -> 24.176344 | H50: =H49*$J$7 -> 24.690614 | I50: =I49*$J$7 -> 25.127239
B53: LESS: After-Tax Interest Expense | E53: =-D50*$D$10*(1-$D$5) -> -0.84603243 | F53: =-E50*$D$10*(1-$D$5) -> -0.85430976 | G53: =-F50*$D$10*(1-$D$5) -> -0.87766778 | H53: =-G50*$D$10*(1-$D$5) -> -0.89914531 | I53: =-H50*$D$10*(1-$D$5) -> -0.91827159 | J53: =-I50*$D$10*(1-$D$5) -> -0.93451018
B54: PLUS: Net Borrowing | D54: =D50 -> 22.748237 | E54: =E50-D50 -> 0.22256193 | F54: =F50-E50 -> 0.62805382 | G54: =G50-F50 -> 0.57749088 | H54: =H50-G50 -> 0.51426998 | I54: =I50-H50 -> 0.43662543 | J54: =J50-I50 -> -25.127239
B55: Equity/Levered FCF | D55: =D33+SUM(D53:D54) -> -350977.25 | E55: =E33+SUM(E53:E54) -> 262569.58 | F55: =F33+SUM(F53:F54) -> 211434.01 | G55: =G33+SUM(G53:G54) -> 226234.33 | H55: =H33+SUM(H53:H54) -> 242070.67 | I55: =I33+SUM(I53:I54) -> 259015.55 | J55: =J33+SUM(J53:J54) -> 3668653.2
B57: NPV of FCFE | C57: =XNPV(D9,D55:J55,D21:J21) -> 2747998.6 | D57: =NPV(D9,E55:K55)+D55 -> 2678129
B58: Check to NPV FCFF | C58: =C57-D36 -> -0.21177216 | D58: =D57-E36 -> 0 | E58: <want to see 0
B60: Example from textbook | C60: Year 0 | D60: Year 1 | E60: Year 2 | F60: Year 3 | G60: Year 4
B61: Unlevered FCF | C61: -29 | D61: 21 | E61: 21 | F61: 21 | G61: 21
B63: Levered Value @7.25% WACC | C63: =(D61+D63)/(1.0725) -> 70.731823 | D63: =(E61+E63)/(1.0725) -> 54.85988 | E63: =(F61+F63)/(1.0725) -> 37.837221 | F63: =G61/(1.0725) -> 19.58042
B64: Debt Capacity @ d=50% | C64: =C63*0.5 -> 35.365911 | D64: =D63*0.5 -> 27.42994 | E64: =E63*0.5 -> 18.918611 | F64: =F63*0.5 -> 9.7902098
B66: LESS After Tax Expense, @ t = 25% and cost of d = 6% | D66: =-C64*0.06*(1-0.25) -> -1.591466 | E66: =-D64*0.06*(1-0.25) -> -1.2343473 | F66: =-E64*0.06*(1-0.25) -> -0.85133747 | G66: =-F64*0.06*(1-0.25) -> -0.44055944
B67: PLUS: Net Borrowing | C67: =C64 -> 35.365911 | D67: =D64-C64 -> -7.9359714 | E67: =E64-D64 -> -8.5113294 | F67: =F64-E64 -> -9.1284007 | G67: =G64-F64 -> -9.7902098
B68: FCFE | C68: =C61+SUM(C66:C67) -> 6.3659113 | D68: =D61+SUM(D66:D67) -> 11.472563 | E68: =E61+SUM(E66:E67) -> 11.254323 | F68: =F61+SUM(F66:F67) -> 11.020262 | G68: =G61+SUM(G66:G67) -> 10.769231

Sheet NPV Calculation_No Payoff
B2: DCF Model
B4: Assumptions | I4: Gross Margin | J4: =Assumptions!B6 -> 0.36
B5: Tax Rate | D5: =Assumptions!B9 -> 0.2284 | I5: Revenues from Investment | J5: 0
B6: Equity Beta | D6: =('Ba Calculation'!L5-('Ba Calculation'!K3*J7))/J6 -> 1.0199981 | I6: We | J6: =D11/SUM($D$11:$D$12) -> 0.99999249
B7: Market risk premium | D7: ='Ba Calculation'!H24 -> 0.0533 | I7: Wd | J7: =D12/SUM($D$11:$D$12) -> 7.509828e-06
B8: Risk free rate | D8: ='Ba Calculation'!H22 -> 0.0421 | I8: Salvage Value | J8: 0
B9: Cost of equity | D9: =D8+D6*D7 -> 0.096465897
B10: Cost of debt | D10: ='FCFE Calculations'!D10 -> 0.0482 | E10: https://ycharts.com/indicators/us_corporate_a_effective_yield
B11: Market value of equity | D11: ='FCFE Calculations'!D11 -> 1332910000000 | E11: https://finance.yahoo.com/quote/ROK/
B12: Net debt | D12: ='FCFE Calculations'!D12 -> 10010000 | E12: https://finance.yahoo.com/quote/ROK/balance-sheet/
B13: WACC | D13: =D12/(D12+D11)*D10*(1-D5)+(D11/(D12+D11))*D9 -> 0.096465452
B14: Perpetual Growth Rate | D14: =Assumptions!B5 -> 0.015
B15: CAGR | D15: =Assumptions!B4 -> 0.07
B16: Upfront investment | D16: ='Cost Data'!G22 -> 351000
B17: Today's date | D17: 46387
B18: Fiscal Year End | D18: 46660
B19: Option: Continue | M19: Option: Abandon in FY27
B20: Discounted Cash Flow | D20: Startup | E20: =YEAR(E21) -> 2027 | F20: =YEAR(F21) -> 2028 | G20: =YEAR(G21) -> 2029 | H20: =YEAR(H21) -> 2030 | I20: =YEAR(I21) -> 2031 | J20: =YEAR(J21) -> 2032 | M20: Discounted Cash Flow | O20: Startup | P20: =YEAR(P21) -> 2027 | Q20: =YEAR(Q21) -> 2028 | R20: =YEAR(R21) -> 2029 | S20: =YEAR(S21) -> 2030 | T20: =YEAR(T21) -> 2031 | U20: =YEAR(U21) -> 2032
B21: Date | D21: =D17 -> 46387 | E21: =DATE(YEAR($D$18)+E22,9,30) -> 46660 | F21: =DATE(YEAR($D$18)+F22,9,30) -> 47026 | G21: =DATE(YEAR($D$18)+G22,9,30) -> 47391 | H21: =DATE(YEAR($D$18)+H22,9,30) -> 47756 | I21: =DATE(YEAR($D$18)+I22,9,30) -> 48121 | J21: =DATE(YEAR($D$18)+J22,9,30) -> 48487 | M21: Date | O21: =D17 -> 46387 | P21: =DATE(YEAR($D$18)+P22,9,30) -> 46660 | Q21: =DATE(YEAR($D$18)+Q22,9,30) -> 47026 | R21: =DATE(YEAR($D$18)+R22,9,30) -> 47391 | S21: =DATE(YEAR($D$18)+S22,9,30) -> 47756 | T21: =DATE(YEAR($D$18)+T22,9,30) -> 48121 | U21: =DATE(YEAR($D$18)+U22,9,30) -> 48487
B22: Time Periods | E22: 0 | F22: =E22+1 -> 1 | G22: =F22+1 -> 2 | H22: =G22+1 -> 3 | I22: =H22+1 -> 4 | J22: 5 | M22: Time Periods | P22: 0 | Q22: =P22+1 -> 1 | R22: =Q22+1 -> 2 | S22: =R22+1 -> 3 | T22: =S22+1 -> 4 | U22: 5
B23: Year Fraction | E23: =YEARFRAC(D21,E21) -> 0.75 | F23: =YEARFRAC(E21,F21) -> 1 | G23: =YEARFRAC(F21,G21) -> 1 | H23: =YEARFRAC(G21,H21) -> 1 | I23: =YEARFRAC(H21,I21) -> 1 | J23: =YEARFRAC(I21,J21) -> 1 | M23: Year Fraction | P23: =YEARFRAC(O21,P21) -> 0.75 | Q23: =YEARFRAC(P21,Q21) -> 1 | R23: =YEARFRAC(Q21,R21) -> 1 | S23: =YEARFRAC(R21,S21) -> 1 | T23: =YEARFRAC(S21,T21) -> 1 | U23: =YEARFRAC(T21,U21) -> 1
B24: Revenue | E24: =J5 -> 0 | F24: =E24*(1+$D$15) -> 0 | G24: =F24*(1+$D$15) -> 0 | H24: =G24*(1+$D$15) -> 0 | I24: =H24*(1+$D$15) -> 0 | J24: =I24*(1+$D$15) -> 0 | K24: =J24*(1+D14) -> 0 | M24: Revenue | P24: =J5 -> 0 | Q24: =0+J8 -> 0 | R24: 0 | S24: 0 | T24: 0 | U24: 0 | V24: 0
B25: Expenses | E25: ='Cost Data'!$B$24 -> 95000 | F25: ='Cost Data'!$B$24 -> 95000 | G25: ='Cost Data'!$B$24 -> 95000 | H25: ='Cost Data'!$B$24 -> 95000 | I25: ='Cost Data'!$B$24 -> 95000 | J25: ='Cost Data'!$B$24 -> 95000 | K25: ='Cost Data'!$B$24 -> 95000 | M25: Expenses | P25: ='Cost Data'!$B$24 -> 95000 | Q25: 0 | R25: 0 | S25: 0 | T25: 0 | U25: 0 | V25: 0
B26: Depreciation | E26: 0 | F26: 0 | G26: 0 | H26: 0 | I26: 0 | J26: 0 | K26: 0 | M26: Depreciation | P26: 0 | Q26: 0 | R26: 0 | S26: 0 | T26: 0 | U26: 0 | V26: 0
B27: EBIT | E27: =E24-E25-E26 -> -95000 | F27: =F24-F25-F26 -> -95000 | G27: =G24-G25-G26 -> -95000 | H27: =H24-H25-H26 -> -95000 | I27: =I24-I25-I26 -> -95000 | J27: =J24-J25-J26 -> -95000 | K27: =K24-K25-K26 -> -95000 | M27: EBIT | P27: =P24-P25-P26 -> -95000 | Q27: =Q24-Q25-Q26 -> 0 | R27: =R24-R25-R26 -> 0 | S27: =S24-S25-S26 -> 0 | T27: =T24-T25-T26 -> 0 | U27: =U24-U25-U26 -> 0 | V27: =V24-V25-V26 -> 0
B28: Less: Taxes | E28: =-E27*$D$5 -> 21698 | F28: =-F27*$D$5 -> 21698 | G28: =-G27*$D$5 -> 21698 | H28: =-H27*$D$5 -> 21698 | I28: =-I27*$D$5 -> 21698 | J28: =-J27*$D$5 -> 21698 | K28: =-K27*$D$5 -> 21698 | M28: Less: Taxes | P28: =-P27*$D$5 -> 21698 | Q28: =-Q27*$D$5 -> 0 | R28: =-R27*$D$5 -> 0 | S28: =-S27*$D$5 -> 0 | T28: =-T27*$D$5 -> 0 | U28: =-U27*$D$5 -> 0 | V28: =-V27*$D$5 -> 0
B29: Plus: D&A | E29: =E26 -> 0 | F29: =F26 -> 0 | G29: =G26 -> 0 | H29: =H26 -> 0 | I29: =I26 -> 0 | J29: =J26 -> 0 | K29: =K26 -> 0 | M29: Plus: D&A | P29: =P26 -> 0 | Q29: =Q26 -> 0 | R29: =R26 -> 0 | S29: =S26 -> 0 | T29: =T26 -> 0 | U29: =U26 -> 0 | V29: =V26 -> 0
B30: Plus: Inc in deferred taxes | E30: 0 | F30: 0 | G30: 0 | H30: 0 | I30: 0 | J30: 0 | K30: 0 | M30: Plus: Inc in deferred taxes | P30: 0 | Q30: 0 | R30: 0 | S30: 0 | T30: 0 | U30: 0 | V30: 0
B31: Less: Capex | D31: =-D16 -> -351000 | M31: Less: Capex | O31: =-D16 -> -351000
B32: Less: Changes in NWC | E32: =-E44 -> 26623.525 | F32: =-F44 -> 0 | G32: =-G44 -> 0 | H32: =-H44 -> 0 | I32: =-I44 -> 0 | J32: =-J44 -> 0 | K32: =-K44 -> 0 | M32: Less: Changes in NWC | P32: =-P44 -> 26623.525 | Q32: =-Q44 -> -26623.525 | R32: =-R44 -> 0 | S32: =-S44 -> 0 | T32: =-T44 -> 0 | U32: =-U44 -> 0 | V32: =-V44 -> 0
B33: Unlevered FCF | D33: =D27+SUM(D28:D32) -> -351000 | E33: =E27+SUM(E28:E32) -> -46678.475 | F33: =F27+SUM(F28:F32) -> -73302 | G33: =G27+SUM(G28:G32) -> -73302 | H33: =H27+SUM(H28:H32) -> -73302 | I33: =I27+SUM(I28:I32) -> -73302 | J33: =J27+SUM(J28:J32)+J34 -> -973094.46 | K33: =K27+SUM(K28:K32) -> -73302 | M33: Unlevered FCF | O33: =O27+SUM(O28:O32) -> -351000 | P33: =P27+SUM(P28:P32) -> -46678.475 | Q33: =Q27+SUM(Q28:Q32) -> -26623.525 | R33: =R27+SUM(R28:R32) -> 0 | S33: =S27+SUM(S28:S32) -> 0 | T33: =T27+SUM(T28:T32) -> 0 | U33: =U27+SUM(U28:U32)+U34 -> 0 | V33: =V27+SUM(V28:V32) -> 0
B34: Terminal Value | J34: =K33/(D13-D14) -> -899792.46 | M34: Terminal Value | U34: =V33/(D13-D14) -> 0
B36: Net Present Value | D36: =XNPV(D13,D33:J33,D21:J21) -> -1185936 | M36: Net Present Value | O36: =XNPV(D13,O33:U33,O21:U21) -> -417230.84
B38: Net Working Capital Forecast | M38: Net Working Capital Forecast
B39: Cash Requirements | D39: 0 | E39: 0 | F39: 0 | G39: 0 | H39: 0 | I39: 0 | J39: 0 | K39: 0 | M39: Cash Requirements | O39: 0 | P39: 0 | Q39: 0 | R39: 0 | S39: 0 | T39: 0 | U39: 0 | V39: 0
B40: PLUS: Inventory | D40: 0 | E40: 0 | F40: 0 | G40: 0 | H40: 0 | I40: 0 | J40: 0 | K40: 0 | M40: PLUS: Inventory | O40: 0 | P40: 0 | Q40: 0 | R40: 0 | S40: 0 | T40: 0 | U40: 0 | V40: 0
B41: PLUS: Receivables @ x% of Sales | D41: 0 | E41: =E24*$C$46 -> 0 | F41: =F24*$C$46 -> 0 | G41: =G24*$C$46 -> 0 | H41: =H24*$C$46 -> 0 | I41: =I24*$C$46 -> 0 | J41: =J24*$C$46 -> 0 | K41: =K24*$C$46 -> 0 | M41: PLUS: Receivables @ x% of Sales | O41: 0 | P41: =P24*$N$46 -> 0 | Q41: =Q24*$N$46 -> 0 | R41: =R24*$N$46 -> 0 | S41: =S24*$N$46 -> 0 | T41: =T24*$N$46 -> 0 | U41: =U24*$N$46 -> 0 | V41: =V24*$N$46 -> 0
B42: LESS: Payables @ x% of COGs | D42: 0 | E42: =-E25*$C$47 -> -26623.525 | F42: =-F25*$C$47 -> -26623.525 | G42: =-G25*$C$47 -> -26623.525 | H42: =-H25*$C$47 -> -26623.525 | I42: =-I25*$C$47 -> -26623.525 | J42: =-J25*$C$47 -> -26623.525 | K42: =-K25*$C$47 -> -26623.525 | M42: LESS: Payables @ x% of COGs | O42: 0 | P42: =-P25*$N$47 -> -26623.525 | Q42: =-Q25*$N$47 -> 0 | R42: =-R25*$N$47 -> 0 | S42: =-S25*$N$47 -> 0 | T42: =-T25*$N$47 -> 0 | U42: =-U25*$N$47 -> 0 | V42: =-V25*$N$47 -> 0
B43: Net Working Capital | D43: =SUM(D39:D42) -> 0 | E43: =SUM(E39:E42) -> -26623.525 | F43: =SUM(F39:F42) -> -26623.525 | G43: =SUM(G39:G42) -> -26623.525 | H43: =SUM(H39:H42) -> -26623.525 | I43: =SUM(I39:I42) -> -26623.525 | J43: =SUM(J39:J42) -> -26623.525 | K43: =SUM(K39:K42) -> -26623.525 | M43: Net Working Capital | O43: =SUM(O39:O42) -> 0 | P43: =SUM(P39:P42) -> -26623.525 | Q43: =SUM(Q39:Q42) -> 0 | R43: =SUM(R39:R42) -> 0 | S43: =SUM(S39:S42) -> 0 | T43: =SUM(T39:T42) -> 0 | U43: =SUM(U39:U42) -> 0 | V43: =SUM(V39:V42) -> 0
B44: Increases in NWC | E44: =E43-D43 -> -26623.525 | F44: =F43-E43 -> 0 | G44: =G43-F43 -> 0 | H44: =H43-G43 -> 0 | I44: =I43-H43 -> 0 | J44: =J43-I43 -> 0 | K44: =K43-J43 -> 0 | M44: Increases in NWC | P44: =P43-O43 -> -26623.525 | Q44: =Q43-P43 -> 26623.525 | R44: =R43-Q43 -> 0 | S44: =S43-R43 -> 0 | T44: =T43-S43 -> 0 | U44: =U43-T43 -> 0 | V44: =V43-U43 -> 0
B46: Receivables % of Sales | C46: ='FCFE Calculations'!C46 -> 0.079335628 | M46: Receivables % of Sales | N46: ='FCFE Calculations'!C46 -> 0.079335628
B47: Payables % of COGS | C47: ='FCFE Calculations'!C47 -> 0.28024763 | M47: Payables % of COGS | N47: ='FCFE Calculations'!C47 -> 0.28024763

Sheet NPV - Option Analysis
B1: Scenario 1: Retention Increases | C1: 0.5 | D1: Continue | E1: ='NPV Calculation_Payoff'!D36 -> 2747998.8 | G1: Probabilities based on AB testing?
D2: Abandon in FY27 | E2: ='NPV Calculation_Payoff'!P36 -> -165071.8
B3: Scenario 2: Retention Remains the Same | C3: =1-C1 -> 0.5 | D3: Continue | E3: ='NPV Calculation_No Payoff'!D36 -> -1185936
D4: Abandon in FY27 | E4: ='NPV Calculation_No Payoff'!O36 -> -417230.84
B6: Expected Value (Abandonment Option) | C6: =C1*E1+C3*E4 -> 1165384
B9: Expected Value (Only Continue) | C9: =C1*E1+C3*E3 -> 781031.4
B10: Value of Abandonment | C10: =C6-C9 -> 384352.56
